{"version":1,"resource":"file:///home/juliohmb/AI/ScreenShoter/screenshooter.py","entries":[{"id":"Egrq.py","timestamp":1670983456626},{"id":"005r.py","timestamp":1670983538449},{"id":"Ba4F.py","timestamp":1670983651026},{"id":"1n6v.py","timestamp":1670983842952},{"id":"HySS.py","timestamp":1670983990918},{"id":"tmOy.py","timestamp":1670984014425},{"id":"G8OZ.py","timestamp":1670984150538},{"id":"6JnQ.py","timestamp":1670984335027},{"id":"T1sc.py","timestamp":1670984410414},{"id":"THq0.py","timestamp":1670984637074}]}